Metadata-Version: 1.1
Name: mongo-pc
Version: 1.0.0
Summary: Funções para manipulação MongoDB
Home-page: UNKNOWN
Author: Fabrício Antoniasse
Author-email: fabricio.antoniasse@hotmail.com
License: MIT
Keywords: mongo_pc
Platform: UNKNOWN
Classifier: Development Status :: 5 - Production/Stable
Classifier: Intended Audience :: Developers
Classifier: License :: OSI Approved :: MIT License
Classifier: Natural Language :: Portuguese (Brazilian)
Classifier: Operating System :: OS Independent
